saadiahmed292/setup.py
saadiahmed292-1.0.0.dist-info/METADATA
saadiahmed292-1.0.0.dist-info/WHEEL
saadiahmed292-1.0.0.dist-info/top_level.txt
saadiahmed292-1.0.0.dist-info/RECORD
