Metadata-Version: 2.1
Name: saadiahmed292
Version: 1.0.0
Summary: An awesome package for demonstration purposes
Home-page: http://pypi.python.org/pypi/saadiahmed292/
Author: Saadi Ahmed
Author-email: ah.saadi@esi-sba.dz
License: LICENSE.txt
